superduper_transformers/__init__.py
superduper_transformers/model.py
superduper_transformers/training.py
superduper_transformers-0.10.0.dist-info/licenses/LICENSE
superduper_transformers-0.10.0.dist-info/METADATA
superduper_transformers-0.10.0.dist-info/WHEEL
superduper_transformers-0.10.0.dist-info/top_level.txt
superduper_transformers-0.10.0.dist-info/RECORD
