Metadata-Version: 2.4
Name: superduper_transformers
Version: 0.10.0
Summary: Transformers is a popular AI framework, and we have incorporated native support for Transformers to provide essential Large Language Model (LLM) capabilities. 
Maintainer-email: "superduper.io, Inc." <opensource@superduper.io>
License: 
Project-URL: homepage, https://superduper.io
Project-URL: documentation, https://docs.superduper.io/docs/intro
Project-URL: source, https://github.com/superduper-io/superduper
Keywords: databases,mongodb,data-science,machine-learning,mlops,vector-database,ai
Requires-Python: >=3.10
License-File: LICENSE
Requires-Dist: sentence-transformers>=2.2.2
Requires-Dist: datasets>=2.18.0
Requires-Dist: peft>=0.10.0
Requires-Dist: trl==0.12.0
Provides-Extra: test
Dynamic: license-file
